mealyfsm.v
module mealyfsm (
	input clk,    // Clock
	input rst,  // Asynchronous reset active low
	input x,
	output y
);

reg y;
reg [1:0]ps;
reg [1:0]ns;
parameter a = 2'b00, b = 2'b01, c = 2'b10;

always @(posedge clk or negedge rst) 
begin 
	if(~rst) 
	begin
		ps = a;
	end 

	else 
	begin
		ps = ns;
	end
end


always @(ps or x) 
begin 
	if(ps == a && x == 0) 
	begin
		ns = a;
	end 

	else if(ps == a && x == 1)
	begin
		ns = b;
	end

	else if(ps == b && x == 0) 
	begin
		ns = a;
	end 

	else if(ps == b && x == 1)
	begin
		ns = c;
	end

	else if(ps == c && x == 0) 
	begin
		ns = a;
	end 

	else if(ps == c && x == 1)
	begin
		ns = c;
	end
end


always @(ps or x) 
begin 
	if(ps == c && x == 1) 
	begin
		y = 1;
	end 

	else 
	begin
		y = 0;
	end
end

endmodule

mealyfsm_tb.v
`timescale 1s/100ms
`include "mealyfsm.v"

module mealyfsm_tb ();

	reg clk;
	reg rst;
	reg x;
	wire y;

	mealyfsm mymealy(clk, rst, x, y);

	initial
	begin 
		$monitor("x = %b, y = %b",x, y);
		$dumpfile("mealyfsm.vcd");
		$dumpvars(0, mealyfsm_tb);

		x <= 0;

		rst <= 1; clk <= 1; #1;
		clk <= 0; #1;

		clk <= 1; #1;
		clk <= 0; #1;

		rst <= 0; clk <= 1; #1;
		clk <= 0; #1;

		clk <= 1; #1;
		clk <= 0; #1;

		rst <= 1; clk <= 1; #1;
		clk <= 0; #1;

		clk <= 1; #1;
		clk <= 0; #1;

		x <= 1;

		clk <= 1; #1;
		clk <= 0; #1;

		rst <= 0; clk <= 1; #1;
		clk <= 0; #1;

		rst <= 1; clk <= 1; #1;
		clk <= 0; #1;

		clk <= 1; #1;
		clk <= 0; #1;

		rst <= 0; clk <= 1; #1;
		clk <= 0; #1;

		clk <= 1; #1;
		clk <= 0; #1;

		clk <= 1; #1;
		clk <= 0; #1;

		rst <= 1; clk <= 1; #1;
		clk <= 0; #1;

		clk <= 1; #1;
		clk <= 0; #1;

		clk <= 1; #1;
		clk <= 0; #1;

		x <= 0;

		clk <= 1; #1;
		clk <= 0; #1;

		rst <= 0; clk <= 1; #1;
		clk <= 0; #1;

		rst <= 1; clk <= 1; #1;
		clk <= 0; #1;

		$finish;
	end

endmodule

mealyfsm.vcd
$date
	Tue Nov 13 23:30:27 2018
$end
$version
	Icarus Verilog
$end
$timescale
	100ms
$end
$scope module mealyfsm_tb $end
$var wire 1 ! y $end
$var reg 1 " clk $end
$var reg 1 # rst $end
$var reg 1 $ x $end
$scope module mymealy $end
$var wire 1 " clk $end
$var wire 1 # rst $end
$var wire 1 $ x $end
$var reg 2 % ns [1:0] $end
$var reg 2 & ps [1:0] $end
$var reg 1 ! y $end
$upscope $end
$upscope $end
$enddefinitions $end
#0
$dumpvars
bx &
bx %
0$
1#
1"
0!
$end
#10
0"
#20
1"
#30
0"
#40
b0 %
b0 &
1"
0#
#50
0"
#60
1"
#70
0"
#80
1"
1#
#90
0"
#100
1"
#110
0"
#120
b1 &
b10 %
1"
1$
#130
0"
#140
b1 %
b0 &
1"
0#
#150
0"
#160
b10 %
b1 &
1"
1#
#170
0"
#180
1!
b10 &
1"
#190
0"
#200
b1 %
0!
b0 &
1"
0#
#210
0"
#220
1"
#230
0"
#240
1"
#250
0"
#260
b10 %
b1 &
1"
1#
#270
0"
#280
1!
b10 &
1"
#290
0"
#300
1"
#310
0"
#320
b0 &
0!
b0 %
1"
0$
#330
0"
#340
1"
0#
#350
0"
#360
1"
1#
